{
  "codes": [
    {
        "name": "How I Fixed My Attention Span | MemeGirls",
        "code": "27472"
    },
    {
        "name": "How to Turn Your Hobby into a Profitable Business? (FULL GUIDE)",
        "code": "22441"
    },
    {
        "name": "Exclusive Airdrop And Freebies in MemeFi: Get While They Last!!",
        "code": "89812"
    },
    {
        "name": "Supercharge Your Crypto: The 3 Types of Liquidity Pools | Part 2 of 5 | MemeFi",
        "code": "69422"
    },
    {
        "name": "The Best Purchases I've EVER Made As A Minimalist | MemeGirls",
        "code": "82115"
    },
    {
        "name": "Think Liquidity Pools Are Risk-Free? Think Again! | Part 3 of 5 | MemeFi",
        "code": "29101"
    }
]
}
